{
  "title": "Orchid Continuum Gallery",
  "description": "A curated collection of orchid specimens and educational content",
  "images": [
    {
      "id": "gary_dsc_2161",
      "src": "/images/gary_collection/DSC_2161.JPG",
      "title": "Orchid Specimen DSC_2161",
      "description": "Beautiful orchid from Gary's collection",
      "category": "gary_collection"
    },
    {
      "id": "gary_dsc_2163",
      "src": "/images/gary_collection/DSC_2163.JPG",
      "title": "Orchid Specimen DSC_2163",
      "description": "Stunning orchid photograph from Gary's collection",
      "category": "gary_collection"
    },
    {
      "id": "gary_dsc_2173",
      "src": "/images/gary_collection/DSC_2173.JPG",
      "title": "Orchid Specimen DSC_2173",
      "description": "Detailed orchid specimen photography",
      "category": "gary_collection"
    },
    {
      "id": "gary_dsc_2219",
      "src": "/images/gary_collection/DSC_2219.JPG",
      "title": "Orchid Specimen DSC_2219",
      "description": "Professional orchid photography",
      "category": "gary_collection"
    },
    {
      "id": "gary_dsc_2240",
      "src": "/images/gary_collection/DSC_2240.JPG",
      "title": "Orchid Specimen DSC_2240",
      "description": "High-quality orchid specimen image",
      "category": "gary_collection"
    },
    {
      "id": "cattleya_1",
      "src": "/images/mahjong_tiles/cattleya_1.png",
      "title": "Cattleya Orchid 1",
      "description": "Cattleya orchid specimen for educational purposes",
      "category": "mahjong_tiles"
    },
    {
      "id": "cattleya_2",
      "src": "/images/mahjong_tiles/cattleya_2.png",
      "title": "Cattleya Orchid 2",
      "description": "Second Cattleya orchid specimen",
      "category": "mahjong_tiles"
    },
    {
      "id": "dendrobium_1",
      "src": "/images/mahjong_tiles/dendrobium_1.png",
      "title": "Dendrobium Orchid 1",
      "description": "Dendrobium orchid specimen for study",
      "category": "mahjong_tiles"
    },
    {
      "id": "dendrobium_2",
      "src": "/images/mahjong_tiles/dendrobium_2.png",
      "title": "Dendrobium Orchid 2",
      "description": "Second Dendrobium orchid specimen",
      "category": "mahjong_tiles"
    },
    {
      "id": "fcos_logo",
      "src": "/images/five_cities_orchid_society_logo.png",
      "title": "Five Cities Orchid Society Logo",
      "description": "Official logo of the Five Cities Orchid Society",
      "category": "logos"
    },
    {
      "id": "orchid_continuum_logo",
      "src": "/images/orchid_continuum_logo.png",
      "title": "Orchid Continuum Logo",
      "description": "Official Orchid Continuum research platform logo",
      "category": "logos"
    },
    {
      "id": "placeholder_orchid",
      "src": "/images/placeholder-orchid.jpg",
      "title": "Placeholder Orchid",
      "description": "Standard orchid placeholder image",
      "category": "placeholders"
    }
  ]
}